Workbook

Sheet Legend + Assumptions
A1: Innovation Project — Customer Requirement Specification (CRS)
A2: Governs an R-Core innovation project run on the eXeL AI platform. ID grammar follows the AMTS Design Traceability Matrix.
A5: HOW TO USE
A6: Blue text | B6: Hardcoded input — edit these.
A7: Yellow fill | B7: Assumption to confirm. Every one is a placeholder until you set it.
A8: Black text | B8: Formula. Do not overwrite.
A10: ID GRAMMAR
A11: CRS-##.IN.SRS.### | B11: Design input — what the customer/business requires.
A12: CRS-##.OUT.SRS.### | B12: Design output — the definable, measurable result.
A13: DR-YYYY.MM.DD-DR.### | B13: Design review.
A14: TR-YYYY.MM.DD-TR.### | B14: Test run.
A15: TR.###_YYYY.MM.DD_IS.### | B15: Test issue raised against a test run.
A16: DT.###_YYYY.MM.DD_PRS.### | B16: Design transfer.
A17: DC.###_YYYY.MM.DD_PRS.### | B17: Design change.
A19: PROGRAM ASSUMPTIONS
A20: Assumption | B20: Value | C20: Source
A21: Projects in program | B21: 9 | C21: Stated by user
A22: Total program funding ($) | B22: 9000000 | C22: Stated by user
A23: Baseline duration per project (months) | B23: 9 | C23: Stated by user
A24: Target compressed duration (months) | B24: 7 | C24: Stated by user
A25: Working days per month | B25: 21 | C25: ASSUMPTION — confirm
A26: Working hours per day | B26: 8 | C26: ASSUMPTION — confirm
A27: Early-delivery pool, minimum (% of program) | B27: 0.1 | C27: Stated by user — floor
A28: Early-delivery pool, target (% of program) | B28: 0.1111 | C28: Stated by user — $1M on $9M
A29: Share of pool to delivery team (%) | B29: 0.6 | C29: PROPOSAL — see CRS-17
A30: Share of pool to gate approvers (%) | B30: 0.25 | C30: PROPOSAL — see CRS-17
A31: Share of pool to risk market (%) | B31: 0.15 | C31: PROPOSAL — see CRS-17
A32: Clawback reserve held to launch (%) | B32: 0.3 | C32: PROPOSAL — see CRS-18

Sheet Incentive Model
A1: Early-Delivery Incentive — self-funding from avoided burn
A2: The pool is paid out of R&D burn that was budgeted and not spent. The sponsor's return is the revenue pulled forward, which is not consumed by the pool.
A4: Program burn rate ($/month) | B4: ='Legend + Assumptions'!$B$22/'Legend + Assumptions'!$B$23 -> 1000000
A5: Program burn rate ($/day) | B5: =B4/'Legend + Assumptions'!$B$25 -> 47619.048
A6: Program burn rate ($/hour) | B6: =B5/'Legend + Assumptions'!$B$26 -> 5952.381
A7: Program burn rate ($/min) — MoT | B7: =B6/60 -> 99.206349
A8: Per-project burn rate ($/min) | B8: =B7/'Legend + Assumptions'!$B$21 -> 11.022928
A10: Months delivered early | B10: ='Legend + Assumptions'!$B$23-'Legend + Assumptions'!$B$24 -> 2
A11: Burn avoided ($) | B11: =B4*B10 -> 2000000
A13: Pool at minimum rate ($) | B13: ='Legend + Assumptions'!$B$22*'Legend + Assumptions'!$B$27*B10 -> 1800000
A14: Pool at target rate ($) | B14: ='Legend + Assumptions'!$B$22*'Legend + Assumptions'!$B$28*B10 -> 1999800
A15: Pool as % of burn avoided (target) | B15: =IFERROR(B14/B11,0) -> 0.9999
A16: Sponsor net on burn alone ($) | B16: =B11-B14 -> 200
A18: Delivery team share ($) | B18: =B14*'Legend + Assumptions'!$B$29 -> 1199880
A19: Gate approver share ($) | B19: =B14*'Legend + Assumptions'!$B$30 -> 499950
A20: Risk market share ($) | B20: =B14*'Legend + Assumptions'!$B$31 -> 299970
A21: Split check (must equal pool) | B21: =B18+B19+B20 -> 1999800
A23: Note: target pool at 2 months early equals the burn avoided exactly. Sponsor return comes from revenue displacement, not from burn. See CRS-17. | B23: =B14*(1-'Legend + Assumptions'!$B$32) -> 1399860
A24: Held to launch, at risk ($) | B24: =B14*'Legend + Assumptions'!$B$32 -> 599940

Sheet Design Matrix
A1: Product Requirements: Design Traceability Matrix — Innovation Project
A2: Plan Stage: Customer User Stories + Customer Requirement Specs | Develop Stage: Team Specification # + Design Output #
A4: Gate | B4: Dev Team | C4: Design Input # | D4: Specification Input: Target at Launch | E4: Market Input: Stretch Target | F4: Design Output # | G4: Design Output: Definable / Measurable | H4: Source
A5: G1 | B5: Software | C5: CRS-75.IN.SRS.040 | D5: Platform is the sole system of record for G1-G7 progression; a gate state that exists only in a deck or email is not a gate state. | E5: External PM tools read gate state from the platform API rather than holding their own. | F5: CRS-75.OUT.SRS.040 | G5: 100% of gate transitions carry a platform event; zero reconstructed from documents. | H5: Vision 2525 design
A6: G1 | B6: Software | C6: CRS-76.IN.SRS.041 | D6: A deliverable advances only when its bound API function completes with a valid payload. No manual status field exists. | E6: Function completion auto-drafts the gate review packet. | F6: CRS-76.OUT.SRS.041 | G6: Zero writable status fields in schema; deliverable state is a fold over the event log, reproducible on replay. | H6: Vision 2525 design
A7: G1 | B7: Software | C7: CRS-77.IN.SRS.042 | D7: Gate transition blocked while any DACI-designated Approver has not signed. Reviewers are advisory and non-blocking. | E7: Approver absence auto-escalates to the Steering Team after a set interval. | F7: CRS-77.OUT.SRS.042 | G7: No gate closes with an outstanding required Approver; escalation fires within the configured interval. | H7: AMTS DACI table
A8: G1 | B8: Software | C8: CRS-78.IN.SRS.043 | D8: All state changes recorded in an append-only event log. Gate Review History is a query over that log. | E8: Any past moment reconstructable for audit or gate review. | F8: CRS-78.OUT.SRS.043 | G8: Replay to any timestamp reproduces the state shown at that time; audit trail and state cannot disagree. | H8: Vision 2525 design
A9: G2 | B9: UX / ID | C9: CRS-79.IN.SRS.044 | D9: Project state renders as a 3x3x3 cube whose cells fill as deliverables are approved. | E9: Portfolio view shows all projects as cubes at a glance. | F9: CRS-79.OUT.SRS.044 | G9: A user identifies stage and blocking gate from the cube alone, without reading text. | H9: Cube Analysis
A10: G2 | B10: Software | C10: CRS-80.IN.SRS.045 | D10: Deliverable groupings always tile exactly 27 cells with every group face-connected. | E10: Partition strategy selectable per project for visual variety. | F10: CRS-80.OUT.SRS.045 | G10: Validator rejects any configuration not summing to 27 or containing a disconnected group; failure throws rather than renders. | H10: Cube Analysis
A11: G2 | B11: Software | C11: CRS-81.IN.SRS.046 | D11: Any authenticated user may submit a risk prediction against any project, gate, or item, regardless of assignment. | E11: External partners and customers may submit under a restricted scope. | F11: CRS-81.OUT.SRS.046 | G11: Submission accepted from users with no role on the target project; median submission time under 60 seconds. | H11: Stated by user
A12: G3 | B12: AI/ML | C12: CRS-82.IN.SRS.047 | D12: Submitted risks are clustered into themes and returned for team voting. | E12: Themes proposed live as submissions arrive rather than on close. | F12: CRS-82.OUT.SRS.047 | G12: 1,000,000 responses themed in under 60 seconds; identical input produces identical themes. | H12: Existing CRS scale target
A13: G3 | B13: Software | C13: CRS-83.IN.SRS.048 | D13: Predictions resolve as materialized, mitigated, superseded, not-borne-out, or unresolvable. Mitigated pays identically to materialized. | E13: Resolution proposed automatically from gate evidence, confirmed by a human resolver. | F13: CRS-83.OUT.SRS.048 | G13: Payout for mitigated equals materialized at equal lead time and specificity; verified by test case. | H13: Prevention paradox fix
A14: G3 | B14: Software | C14: CRS-84.IN.SRS.049 | D14: Predictor, actioner, and resolver enforced as distinct identities on any prediction. Predictions require a stake. | E14: Stake size set by the predictor as a confidence signal. | F14: CRS-84.OUT.SRS.049 | G14: Zero predictions resolve where any two roles share an identity; 100% of scored predictions carry a stake. | H14: Anti-gaming control
A15: G3 | B15: Software | C15: CRS-85.IN.SRS.050 | D15: Every item carries planned and actual time start and time stop. No item exists without both planned values. | E15: Actuals captured from function events rather than self-reported. | F15: CRS-85.OUT.SRS.050 | G15: 100% of items have planned start and stop at gate entry; actuals present for all closed items. | H15: Stated by user
... A23: G6 | B23: HR Planning | C23: CRS-93.IN.SRS.058 | D23: Intelligence load tracked across AI, SI, and HI contribution per team, with sustained human-load thresholds acting as a burnout guard that reduces or voids upside payout. | E23: Load trend predicts burnout risk before the threshold is crossed. | F23: CRS-93.OUT.SRS.058 | G23: Upside earned above the human-load threshold is withheld pending review; guard is enforcing, not advisory. SI measurement rule PENDING DEFINITION. | H23: Stated by user

Sheet Verification
A1: Qualify Stage: Design Matrix — Design Review # + Test Run #
A2: One row per verification event. Fill as reviews and test runs occur.
A4: Design Input # | B4: Design Review # | C4: Design Review Plan | D4: Verification & Validation Plan | E4: Test Run # | F4: Test Issues | G4: Test Issue Description
A5: CRS-05.IN.SRS.005 | B5: DR-2026.09.14-DR.001 | C5: Theming determinism review with AI/ML + Software | D5: Replay 1M-response corpus 3x; compare theme sets byte-for-byte | E5: TR-2026.09.28-TR.001 | F5: TR.001_2026.09.28_IS.001 | G5: Run 3 produced 41 themes vs 40; non-determinism traced to provider ordering
A6: ^ example row — replace

Sheet Transfer + Change
A1: Launch Stage: Design Matrix — Design Transfer + Design Change
A3: Design Input # | B3: Design Transfer | C3: Design Transfer Confirmation | D3: Design Change | E3: Design Change Description
A4: CRS-10.IN.SRS.010 | B4: DT.001_2026.11.02_PRS.001 | C4: Cascade engine handed to Ops, signed by R&D | D4: DC.001_2026.11.18_PRS.001 | E4: Budget calendar added to cascade after FP&A review
A5: ^ example row — replace

Sheet Gate Map
A1: Gate Map — 27 cells across G1-G7
A2: partition(7) yields 4,4,4,4,4,4,3. CRS entries occupy cells; remaining cells are filled by AMTS Recommended items and Design Matrix artifacts.
A4: Gate | B4: Stage | C4: Cells (from partition) | D4: CRS assigned | E4: Cells unassigned
A5: G1 | B5: Concept | C5: 4 | D5: =COUNTIF('Design Matrix'!$A$5:$A$23,A5) -> 4 | E5: =C5-D5 -> 0
A6: G2 | B6: Plan | C6: 4 | D6: =COUNTIF('Design Matrix'!$A$5:$A$23,A6) -> 3 | E6: =C6-D6 -> 1
A7: G3 | B7: Develop | C7: 4 | D7: =COUNTIF('Design Matrix'!$A$5:$A$23,A7) -> 4 | E7: =C7-D7 -> 0
A8: G4 | B8: Qualify | C8: 4 | D8: =COUNTIF('Design Matrix'!$A$5:$A$23,A8) -> 4 | E8: =C8-D8 -> 0
A9: G5 | B9: Launch | C9: 4 | D9: =COUNTIF('Design Matrix'!$A$5:$A$23,A9) -> 3 | E9: =C9-D9 -> 1
A10: G6 | B10: Maximize | C10: 4 | D10: =COUNTIF('Design Matrix'!$A$5:$A$23,A10) -> 1 | E10: =C10-D10 -> 3
A11: G7 | B11: Retire / EOL | C11: 3 | D11: =COUNTIF('Design Matrix'!$A$5:$A$23,A11) -> 0 | E11: =C11-D11 -> 3
B12: TOTAL | C12: =SUM(C5:C11) -> 27 | D12: =SUM(D5:D11) -> 19 | E12: =SUM(E5:E11) -> 8
B13: Cube check (must be 27) | C13: =IF(C12=27,"OK","MISMATCH") -> OK
